{
  "_comment": "Mapping for markers_opt_biomech_.xml sites from SAM3DBody MHR mesh.",

  "r_asis":             {"match_type": "vertex",          "index": 7694,    "confidence_weight": 0.5,  "offset_category": "bony_landmark"},
  "l_asis":             {"match_type": "vertex",          "index": 6533,    "confidence_weight": 0.5,  "offset_category": "bony_landmark"},
  "r_psis":             {"match_type": "vertex",          "index": 7321,    "confidence_weight": 0.5,  "offset_category": "bony_landmark"},
  "l_psis":             {"match_type": "vertex",          "index": 6214,    "confidence_weight": 0.5,  "offset_category": "bony_landmark"},
  "c_sacrum":           {"match_type": "kinematic_node",  "index": 34,      "confidence_weight": 0.5,  "offset_category": "bony_landmark"},
  "r_hip":              {"match_type": "kinematic_node",  "index": 18,      "confidence_weight": 0.9,  "offset_category": "joint_center"},
  "l_hip":              {"match_type": "kinematic_node",  "index": 2,       "confidence_weight": 0.9,  "offset_category": "joint_center"},
  "sacrum":             {"match_type": "vertex",          "index": 5733,    "confidence_weight": 0.4,  "offset_category": "bony_landmark"},

  "l_gtro":             {"match_type": "vertex",          "index": 6074,    "confidence_weight": 0.5,  "offset_category": "bony_landmark"},
  "l_prox_femur_ant":   {"match_type": "vertex",          "index": 11378,   "confidence_weight": 0.3,  "offset_category": "soft_tissue"},
  "l_dist_femur_ant":   {"match_type": "vertex",          "index": 11492,   "confidence_weight": 0.3,  "offset_category": "soft_tissue"},
  "l_femur_lat":        {"match_type": "vertex",          "index": 11482,   "confidence_weight": 0.3,  "offset_category": "soft_tissue"},
  "l_knee":             {"match_type": "kinematic_node",  "index": 3,       "confidence_weight": 0.9,  "offset_category": "joint_center"},
  "l_knee_lat":         {"match_type": "vertex",          "index": 11544,   "confidence_weight": 0.7,  "offset_category": "bony_landmark"},
  "l_knee_med":         {"match_type": "vertex",          "index": 11662,   "confidence_weight": 0.7,  "offset_category": "bony_landmark"},


  "l_shin_lat":         {"match_type": "vertex",          "index": 11708,   "confidence_weight": 0.3,  "offset_category": "soft_tissue"},
  "l_shin_prox":        {"match_type": "vertex",          "index": 11750,   "confidence_weight": 0.3,  "offset_category": "soft_tissue"},
  "l_shin_dist":        {"match_type": "vertex",          "index": 11958,   "confidence_weight": 0.3,  "offset_category": "soft_tissue"},
  "l_ankle_lat":        {"match_type": "vertex",          "index": 12223,   "confidence_weight": 0.7,  "offset_category": "bony_landmark"},
  "l_ankle":            {"match_type": "kinematic_node",  "index": 4,       "confidence_weight": 0.9,  "offset_category": "joint_center"},
  "l_ankle_med":        {"match_type": "vertex",          "index": 12235,   "confidence_weight": 0.7,  "offset_category": "bony_landmark"},

  "l_heel":             {"match_type": "vertex",          "index": 12376,   "confidence_weight": 0.5,  "offset_category": "bony_landmark"},
  "l_fmt1":             {"match_type": "vertex",          "index": 12838,   "confidence_weight": 0.4,  "offset_category": "bony_landmark"},
  "l_fmt5":             {"match_type": "vertex",          "index": 12648,   "confidence_weight": 0.4,  "offset_category": "bony_landmark"},
  "l_midfoot_lat":      {"match_type": "vertex",          "index": 12384,   "confidence_weight": 0.3,  "offset_category": "bony_landmark"},

  "l_big_toe":          {"match_type": "vertex",          "index": 13182,   "confidence_weight": 0.5,  "offset_category": "bony_landmark"},
  "l_2nd_toe":          {"match_type": "vertex",          "index": 13264,   "confidence_weight": 0.4,  "offset_category": "bony_landmark"},
  "l_5th_toe":          {"match_type": "vertex",          "index": 13209,   "confidence_weight": 0.4,  "offset_category": "bony_landmark"},

  "r_gtro":             {"match_type": "vertex",          "index": 7219,    "confidence_weight": 0.5,  "offset_category": "bony_landmark"},
  "r_prox_femur_ant":   {"match_type": "vertex",          "index": 16564,   "confidence_weight": 0.3,  "offset_category": "soft_tissue"},
  "r_dist_femur_ant":   {"match_type": "vertex",          "index": 16700,   "confidence_weight": 0.3,  "offset_category": "soft_tissue"},
  "r_femur_lat":        {"match_type": "vertex",          "index": 16655,   "confidence_weight": 0.3,  "offset_category": "soft_tissue"},
  "r_knee":             {"match_type": "kinematic_node",  "index": 19,      "confidence_weight": 0.9,  "offset_category": "joint_center"},
  "r_knee_lat":         {"match_type": "vertex",          "index": 16745,   "confidence_weight": 0.7,  "offset_category": "bony_landmark"},
  "r_knee_med":         {"match_type": "vertex",          "index": 16819,   "confidence_weight": 0.7,  "offset_category": "bony_landmark"},

  "r_shin_lat":         {"match_type": "vertex",          "index": 16901,   "confidence_weight": 0.3,  "offset_category": "soft_tissue"},
  "r_shin_prox":        {"match_type": "vertex",          "index": 16923,   "confidence_weight": 0.3,  "offset_category": "soft_tissue"},
  "r_shin_dist":        {"match_type": "vertex",          "index": 17115,   "confidence_weight": 0.3,  "offset_category": "soft_tissue"},
  "r_ankle_lat":        {"match_type": "vertex",          "index": 17420,   "confidence_weight": 0.7,  "offset_category": "bony_landmark"},
  "r_ankle":            {"match_type": "kinematic_node",  "index": 21,      "confidence_weight": 0.9,  "offset_category": "joint_center"},
  "r_ankle_med":        {"match_type": "vertex",          "index": 17408,   "confidence_weight": 0.7,  "offset_category": "bony_landmark"},

  "r_heel":             {"match_type": "vertex",          "index": 17522,   "confidence_weight": 0.5,  "offset_category": "bony_landmark"},
  "r_fmt1":             {"match_type": "vertex",          "index": 17991,   "confidence_weight": 0.4,  "offset_category": "bony_landmark"},
  "r_fmt5":             {"match_type": "vertex",          "index": 17841,   "confidence_weight": 0.4,  "offset_category": "bony_landmark"},
  "r_midfoot_lat":      {"match_type": "vertex",          "index": 17554,   "confidence_weight": 0.3,  "offset_category": "bony_landmark"},

  "r_big_toe":          {"match_type": "vertex",          "index": 18379,   "confidence_weight": 0.5,  "offset_category": "bony_landmark"},
  "r_2nd_toe":          {"match_type": "vertex",          "index": 18425,   "confidence_weight": 0.4,  "offset_category": "bony_landmark"},
  "r_5th_toe":          {"match_type": "vertex",          "index": 18394,   "confidence_weight": 0.4,  "offset_category": "bony_landmark"},

  "sternum_sup":        {"match_type": "vertex",          "index": 2853,   "confidence_weight": 0.5,  "offset_category": "bony_landmark"},
  "sternum_inf":        {"match_type": "vertex",          "index": 5698,   "confidence_weight": 0.4,  "offset_category": "bony_landmark"},
  "umbilicus":          {"match_type": "vertex",          "index": 5711,   "confidence_weight": 0.5,  "offset_category": "soft_tissue"},
  "mid_back":           {"match_type": "vertex",          "index": 5753,   "confidence_weight": 0.4,  "offset_category": "bony_landmark"},
  "low_back":           {"match_type": "vertex",          "index": 5745,   "confidence_weight": 0.3,  "offset_category": "bony_landmark"},
  "L1":                 {"match_type": "kinematic_node",  "index": 35,     "confidence_weight": 0.5,  "offset_category": "bony_landmark"},
  "L5":                 {"match_type": "kinematic_node",  "index": 34,     "confidence_weight": 0.5,  "offset_category": "bony_landmark"},
  "r_scapula_sup":      {"match_type": "vertex",          "index": 7175,   "confidence_weight": 0.5,  "offset_category": "soft_tissue"},
  "r_scapula_inf":      {"match_type": "vertex",          "index": 7175,   "confidence_weight": 0.3,  "offset_category": "soft_tissue"},
  "l_scapula_sup":      {"match_type": "vertex",          "index": 6118,   "confidence_weight": 0.5,  "offset_category": "soft_tissue"},
  "l_scapula_inf":      {"match_type": "vertex",          "index": 6118,   "confidence_weight": 0.3,  "offset_category": "soft_tissue"},
  "r_rib_6":            {"match_type": "vertex",          "index": 7378,   "confidence_weight": 0.4,  "offset_category": "soft_tissue"},
  "l_rib_6":            {"match_type": "vertex",          "index": 6157,   "confidence_weight": 0.4,  "offset_category": "soft_tissue"},
  "r_rib_10":           {"match_type": "vertex",          "index": 7849,   "confidence_weight": 0.3,  "offset_category": "soft_tissue"},
  "l_rib_10":           {"match_type": "vertex",          "index": 6649,   "confidence_weight": 0.3,  "offset_category": "soft_tissue"},
  "back_neck":          {"match_type": "vertex",          "index": 5770,   "confidence_weight": 0.5,  "offset_category": "bony_landmark"},
  "C2":                 {"match_type": "kinematic_node",  "index": 113,    "confidence_weight": 0.3,  "offset_category": "bony_landmark"},
  "C7":                 {"match_type": "kinematic_node",  "index": 111,    "confidence_weight": 0.4,  "offset_category": "bony_landmark"},
  
  "top_head":           {"match_type": "kinematic_node",  "index": 126,    "confidence_weight": 0.7,  "offset_category": "bony_landmark"},
  "r_ear":              {"match_type": "sam3d_kp",        "index": 4,      "confidence_weight": 0.5,  "offset_category": "bony_landmark"},
  "l_ear":              {"match_type": "sam3d_kp",        "index": 3,      "confidence_weight": 0.5,  "offset_category": "bony_landmark"},
  "nose":               {"match_type": "sam3d_kp",        "index": 0,      "confidence_weight": 0.7,  "offset_category": "bony_landmark"},
  "chin":               {"match_type": "kinematic_node",  "index": 116,    "confidence_weight": 0.5,  "offset_category": "bony_landmark"},
  "l_eye":              {"match_type": "kinematic_node",  "index": 125,    "confidence_weight": 0.7,  "offset_category": "bony_landmark"},
  "r_eye":              {"match_type": "kinematic_node",  "index": 123,    "confidence_weight": 0.7,  "offset_category": "bony_landmark"},
  "head_post":          {"match_type": "vertex",          "index": 2819,   "confidence_weight": 0.5,  "offset_category": "bony_landmark"},

  "l_shoulder":         {"match_type": "kinematic_node",  "index": 75,     "confidence_weight": 0.8,  "offset_category": "joint_center"},
  "l_prox_humerus":     {"match_type": "vertex",          "index": 6783,   "confidence_weight": 0.3,  "offset_category": "soft_tissue"},
  "l_dist_humerus":     {"match_type": "vertex",          "index": 8174,   "confidence_weight": 0.3,  "offset_category": "soft_tissue"},
  "l_elbow":            {"match_type": "sam3d_kp",        "index": 7,      "confidence_weight": 0.8,  "offset_category": "joint_center"},
  "l_elbow_med":        {"match_type": "vertex",          "index": 8294,   "confidence_weight": 0.5,  "offset_category": "bony_landmark"},
  "l_elbow_lat":        {"match_type": "vertex",          "index": 8380,   "confidence_weight": 0.5,  "offset_category": "bony_landmark"},

  "l_ulna":             {"match_type": "vertex",          "index": 8609,   "confidence_weight": 0.3,  "offset_category": "soft_tissue"},

  "l_radius":           {"match_type": "vertex",          "index": 8598,   "confidence_weight": 0.3,  "offset_category": "soft_tissue"},

  "l_wrist_thumbside":  {"match_type": "vertex",          "index": 8895,   "confidence_weight": 0.5,  "offset_category": "bony_landmark"},
  "l_wrist_pinkieside": {"match_type": "vertex",          "index": 8906,   "confidence_weight": 0.5,  "offset_category": "bony_landmark"},
  "l_wrist":            {"match_type": "kinematic_node",  "index": 77,     "confidence_weight": 0.5,  "offset_category": "joint_center"},
  "l_hand":             {"match_type": "vertex",          "index": 9338,   "confidence_weight": 0.5,  "offset_category": "bony_landmark"},
  "l_fin":              {"match_type": "vertex",          "index": 9216,   "confidence_weight": 0.5,  "offset_category": "bony_landmark"},
  "l_thumb":            {"match_type": "vertex",          "index": 9123,   "confidence_weight": 0.5,  "offset_category": "bony_landmark"},

  "r_shoulder":         {"match_type": "kinematic_node",  "index": 39,     "confidence_weight": 0.8,  "offset_category": "joint_center"},
  "r_prox_humerus":     {"match_type": "vertex",          "index": 7904,   "confidence_weight": 0.3,  "offset_category": "soft_tissue"},
  "r_dist_humerus":     {"match_type": "vertex",          "index": 13349,  "confidence_weight": 0.3,  "offset_category": "soft_tissue"},
  "r_elbow":            {"match_type": "sam3d_kp",        "index": 8,      "confidence_weight": 0.8,  "offset_category": "joint_center"},
  "r_elbow_med":        {"match_type": "vertex",          "index": 13512,  "confidence_weight": 0.5,  "offset_category": "bony_landmark"},
  "r_elbow_lat":        {"match_type": "vertex",          "index": 13523,  "confidence_weight": 0.5,  "offset_category": "bony_landmark"},

  "r_ulna":             {"match_type": "vertex",          "index": 13795,  "confidence_weight": 0.3,  "offset_category": "soft_tissue"},

  "r_radius":           {"match_type": "vertex",          "index": 13778,  "confidence_weight": 0.3,  "offset_category": "soft_tissue"},

  "r_wrist_thumbside":  {"match_type": "vertex",          "index": 14103,  "confidence_weight": 0.5,  "offset_category": "bony_landmark"},
  "r_wrist_pinkieside": {"match_type": "vertex",          "index": 14092,  "confidence_weight": 0.5,  "offset_category": "bony_landmark"},
  "r_wrist":            {"match_type": "kinematic_node",  "index": 41,     "confidence_weight": 0.5,  "offset_category": "joint_center"},
  "r_hand":             {"match_type": "vertex",          "index": 14570,  "confidence_weight": 0.5,  "offset_category": "bony_landmark"},
  "r_fin":              {"match_type": "vertex",          "index": 14406,  "confidence_weight": 0.5,  "offset_category": "bony_landmark"},
  "r_thumb":            {"match_type": "vertex",          "index": 14284,  "confidence_weight": 0.5,  "offset_category": "bony_landmark"}
}
